flake8_import_order_spoqa.py
flake8_import_order_spoqa-1.5.0.dist-info/METADATA
flake8_import_order_spoqa-1.5.0.dist-info/RECORD
flake8_import_order_spoqa-1.5.0.dist-info/WHEEL
flake8_import_order_spoqa-1.5.0.dist-info/entry_points.txt
flake8_import_order_spoqa-1.5.0.dist-info/top_level.txt
